accessibletranslator/__init__.py
accessibletranslator/api_client.py
accessibletranslator/api_response.py
accessibletranslator/configuration.py
accessibletranslator/exceptions.py
accessibletranslator/py.typed
accessibletranslator/rest.py
accessibletranslator/api/__init__.py
accessibletranslator/api/system_api.py
accessibletranslator/api/translation_api.py
accessibletranslator/api/user_management_api.py
accessibletranslator/models/__init__.py
accessibletranslator/models/basic_health_check.py
accessibletranslator/models/function_info.py
accessibletranslator/models/http_validation_error.py
accessibletranslator/models/target_languages_response.py
accessibletranslator/models/token_verification_response.py
accessibletranslator/models/transformation_info.py
accessibletranslator/models/transformations_response.py
accessibletranslator/models/translation_request.py
accessibletranslator/models/translation_response.py
accessibletranslator/models/user_profile_response.py
accessibletranslator/models/validation_error.py
accessibletranslator/models/validation_error_loc_inner.py
accessibletranslator/models/word_balance_response.py
accessibletranslator-1.1.2.dist-info/METADATA
accessibletranslator-1.1.2.dist-info/WHEEL
accessibletranslator-1.1.2.dist-info/top_level.txt
accessibletranslator-1.1.2.dist-info/RECORD
